visiomode/__about__.py
visiomode/__init__.py
visiomode/config.py
visiomode/core.py
visiomode/mixins.py
visiomode/models.py
visiomode/plugins.py
visiomode/devices/__init__.py
visiomode/devices/lever_push.py
visiomode/devices/touchscreen.py
visiomode/devices/water_reward.py
visiomode/protocols/__init__.py
visiomode/protocols/gonogo.py
visiomode/protocols/tafc.py
visiomode/protocols/target_only.py
visiomode/res/__init__.py
visiomode/res/icon.png
visiomode/res/loading.png
visiomode/res/target.jpg
visiomode/stimuli/__init__.py
visiomode/stimuli/grating.py
visiomode/stimuli/isoluminant_gray.py
visiomode/stimuli/moving_grating.py
visiomode/stimuli/solid_colour.py
visiomode/stimuli/variable_contrast_grating.py
visiomode/stimuli/variable_contrast_moving_grating.py
visiomode/webpanel/__init__.py
visiomode/webpanel/api.py
visiomode/webpanel/export.py
visiomode/webpanel/static/favicon.ico
visiomode/webpanel/static/bootstrap/css/bootstrap.min.css
visiomode/webpanel/static/bootstrap/js/bootstrap.min.js
visiomode/webpanel/static/css/styles.min.css
visiomode/webpanel/static/fonts/fa-brands-400.eot
visiomode/webpanel/static/fonts/fa-brands-400.svg
visiomode/webpanel/static/fonts/fa-brands-400.ttf
visiomode/webpanel/static/fonts/fa-brands-400.woff
visiomode/webpanel/static/fonts/fa-brands-400.woff2
visiomode/webpanel/static/fonts/fa-regular-400.eot
visiomode/webpanel/static/fonts/fa-regular-400.svg
visiomode/webpanel/static/fonts/fa-regular-400.ttf
visiomode/webpanel/static/fonts/fa-regular-400.woff
visiomode/webpanel/static/fonts/fa-regular-400.woff2
visiomode/webpanel/static/fonts/fa-solid-900.eot
visiomode/webpanel/static/fonts/fa-solid-900.svg
visiomode/webpanel/static/fonts/fa-solid-900.ttf
visiomode/webpanel/static/fonts/fa-solid-900.woff
visiomode/webpanel/static/fonts/fa-solid-900.woff2
visiomode/webpanel/static/fonts/fontawesome-all.min.css
visiomode/webpanel/static/img/visiomode_logo_icon.png
visiomode/webpanel/static/img/avatars/avatar1.jpeg
visiomode-0.6.0.dist-info/METADATA
visiomode-0.6.0.dist-info/WHEEL
visiomode-0.6.0.dist-info/entry_points.txt
visiomode-0.6.0.dist-info/licenses/LICENSE
visiomode-0.6.0.dist-info/RECORD
