Metadata-Version: 2.3
Name: visiomode
Version: 0.6.0
Summary: An open-source platform for touchscreen-based visuomotor tasks in rodents.
Project-URL: Website, https://www.visiomode.org
Project-URL: Documentation, https:/docs.visiomode.org
Project-URL: Issues, https://github.com/DuguidLab/visiomode/issues
Project-URL: Source, https://github.com/DuguidLab/visiomode
Author-email: Constantinos Eleftheriou <Constantinos.Eleftheriou@ed.ac.uk>
License: MIT License
License-File: LICENSE
Keywords: behaviour,neuroscience,rodent,touchscreen
Classifier: Development Status :: 2 - Pre-Alpha
Classifier: Framework :: Flask
Classifier: Intended Audience :: Science/Research
Classifier: License :: OSI Approved :: MIT License
Classifier: Operating System :: POSIX :: Linux
Classifier: Programming Language :: Python :: 3.9
Classifier: Topic :: Scientific/Engineering
Classifier: Topic :: Scientific/Engineering :: Medical Science Apps.
Classifier: Topic :: Software Development :: Libraries :: pygame
Requires-Python: >=3.9
Requires-Dist: flask>=2.0.3
Requires-Dist: numpy>=1.22
Requires-Dist: pygame>=2.5.1
Requires-Dist: pynwb>=2.2.0
Requires-Dist: pyserial>=3.5
Requires-Dist: pyyaml>=6.0
Requires-Dist: werkzeug<3.0,>=2.2
